drift/__init__.py
drift/admin.py
drift/fields.py
drift/forms.py
drift/models.py
drift/urls.py
drift/views.py
drift/widgets.py
drift/content/__init__.py
drift/content/base.py
drift/content/editor.py
drift/contrib/__init__.py
drift/contrib/flatpages/__init__.py
drift/contrib/flatpages/admin.py
drift/contrib/flatpages/content.py
drift/contrib/flatpages/forms.py
drift/contrib/flatpages/models.py
drift/contrib/flatpages/urls.py
drift/contrib/flatpages/views.py
drift/contrib/flatpages/templates/flatpages/default.html
drift/contrib/flatpages/templates/flatpages/default_edit.html
drift/contrib/versionedpages/__init__.py
drift/contrib/versionedpages/admin.py
drift/contrib/versionedpages/content.py
drift/contrib/versionedpages/forms.py
drift/contrib/versionedpages/models.py
drift/contrib/versionedpages/urls.py
drift/contrib/versionedpages/views.py
drift/contrib/versionedpages/templates/versionedpages/_history_panel.html
drift/contrib/versionedpages/templates/versionedpages/default.html
drift/contrib/versionedpages/templates/versionedpages/edit.html
drift/contrib/versionedpages/templates/versionedpages/versioned_control_panel.html
drift/static/css/content.css
drift/static/css/datepicker.css
drift/static/js/.DS_Store
drift/static/js/content.js
drift/static/js/csrf.js
drift/static/js/flatpagecms.js
drift/static/js/lib/bootstrap-datepicker.js
drift/static/vendor/bootstrap-wysiwyg/bootstrap-wysiwyg.js
drift/static/vendor/bootstrap-wysiwyg/bootstrap-wysiwyg.min.js
drift/static/vendor/bootstrap-wysiwyg/external/jquery.hotkeys.js
drift/static/vendor/bootstrap-wysiwyg/external/google-code-prettify/lang-apollo.js
drift/static/vendor/bootstrap-wysiwyg/external/google-code-prettify/lang-basic.js
drift/static/vendor/bootstrap-wysiwyg/external/google-code-prettify/lang-clj.js
drift/static/vendor/bootstrap-wysiwyg/external/google-code-prettify/lang-css.js
drift/static/vendor/bootstrap-wysiwyg/external/google-code-prettify/lang-dart.js
drift-0.0.5.dist-info/DESCRIPTION.rst
drift-0.0.5.dist-info/METADATA
drift-0.0.5.dist-info/metadata.json
drift-0.0.5.dist-info/RECORD
drift-0.0.5.dist-info/top_level.txt
drift-0.0.5.dist-info/WHEEL
