Metadata-Version: 2.0
Name: drift
Version: 0.0.5
Summary: Make editing content directly easier for CMS authors and users.
Home-page: https://bitbucket.org/amjoconn/drift
Author: Albert O'Connor
Author-email: info@albertoconnor.ca
License: MIT
Platform: UNKNOWN
Classifier: Development Status :: 3 - Alpha
Classifier: Intended Audience :: Developers
Classifier: Natural Language :: English
Classifier: Programming Language :: Python
Classifier: Programming Language :: Python :: 2.7
